{
    "heroContent": {
        "ES": {
            "title": "Brian Benegas",
            "typewriter": [
                "Desarrollador de Software",
                "Código Funcional, Diseño Intuitivo",
                "Desarrollador de Aplicaciones Enterprise",
                "Optimizando la Experiencia de Usuario",
                "Especialista en Soluciones Lógicas",
                "Desarrollo Full-Stack",
                "De la Idea al Despliegue",
                "Arquitecturas de Software Sólidas"
            ]
        },
        "EN": {
            "title": "Brian Benegas",
            "typewriter": [
                "Software Developer",
                "Functional Code, Intuitive Design",
                "Enterprise Application Developer",
                "Optimizing User Experience",
                "Logical Solutions Specialist",
                "Full-Stack Development",
                "From Idea to Deployment",
                "Robust Software Architectures"
            ]
        },
        "FR": {
            "title": "Brian Benegas",
            "typewriter": [
                "Développeur de Logiciels",
                "Code Fonctionnel, Conception Intuitive",
                "Développeur d'Applications d'Entreprise",
                "Optimisation de l'Expérience Utilisateur",
                "Spécialiste en Solutions Logiques",
                "Développement Full-Stack",
                "De l'Idée au Déploiement",
                "Architectures Logicielles Robustes"
            ]
        },
        "DE": {
            "title": "Brian Benegas",
            "typewriter": [
                "Softwareentwickler",
                "Funktionaler Code, Intuitives Design",
                "Entwickler für Unternehmensanwendungen",
                "Optimierung der Benutzererfahrung",
                "Spezialist für logische Lösungen",
                "Full-Stack-Entwicklung",
                "Von der Idee bis zur Bereitstellung",
                "Robuste Softwarearchitekturen"
            ]
        },
        "JP": {
            "title": "ブライアン・ベネガス",
            "typewriter": [
                "ソフトウェア開発者",
                "機能的なコード、直感的なデザイン",
                "エンタープライズアプリケーション開発者",
                "ユーザーエクスペリエンスの最適化",
                "論理的ソリューションの専門家",
                "フルスタック開発",
                "アイデアから展開まで",
                "堅牢なソフトウェアアーキテクチャ"
            ]
        }
    }
}

